SubTrack/__init__.py
SubTrack/main.py
SubTrack/utils.py
SubTrack-0.1.0.dist-info/LICENSE
SubTrack-0.1.0.dist-info/METADATA
SubTrack-0.1.0.dist-info/WHEEL
SubTrack-0.1.0.dist-info/top_level.txt
SubTrack-0.1.0.dist-info/RECORD
